CHANGELOG.rst
COPYRIGHT.rst
LICENSE
MANIFEST.in
README
README.rst
setup.cfg
setup.py
doc/ExtendedAppiumLibrary.html
src/ExtendedAppiumLibrary/__init__.py
src/ExtendedAppiumLibrary/version.py
src/ExtendedAppiumLibrary/locators/__init__.py
src/ExtendedAppiumLibrary/locators/extendedelementfinder.py
src/robotframework_extendedappiumlibrary.egg-info/PKG-INFO
src/robotframework_extendedappiumlibrary.egg-info/SOURCES.txt
src/robotframework_extendedappiumlibrary.egg-info/dependency_links.txt
src/robotframework_extendedappiumlibrary.egg-info/pbr.json
src/robotframework_extendedappiumlibrary.egg-info/requires.txt
src/robotframework_extendedappiumlibrary.egg-info/top_level.txt