Metadata-Version: 1.1
Name: robotframework-extendedappiumlibrary
Version: 0.1.7
Summary: Extended Appium mobile native app testing library for Robot Framework with iOS UI Automation and Android UI Automator support
Home-page: https://github.com/rickypc/robotframework-extendedappiumlibrary
Author: Richard Huang
Author-email: rickypc@users.noreply.github.com
License: AGPL 3
Keywords: robot framework extended testing automation appium mobile ios android uiautomation uiautomator native app apptesting softwaretesting appdev webdev selenium selenium2 webdriver
Platform: any
Classifier: Development Status :: 4 - Beta
Classifier: Intended Audience :: Developers
Classifier: Topic :: Software Development :: Testing
Classifier: License :: OSI Approved :: GNU Affero General Public License v3
Classifier: Programming Language :: Python :: 2.7
